setup.py
dc_ucs.egg-info/PKG-INFO
dc_ucs.egg-info/SOURCES.txt
dc_ucs.egg-info/dependency_links.txt
dc_ucs.egg-info/entry_points.txt
dc_ucs.egg-info/requires.txt
dc_ucs.egg-info/top_level.txt
ucs/__init__.py
ucs/apphelpers.py
ucs/config.py
ucs/database.py
ucs/dce.py
ucs/ucsclean.py
ucs/userhelp.py