Metadata-Version: 1.0
Name: dc-ucs
Version: 0.1.4
Summary: UCS user clean tool
Home-page: https://github.com/donggangcj/ucs.git
Author: GangDong
Author-email: donggangcj@gmail.com
License: MIT Licence
Keywords: pip,UCS,COMMAND LINE
Platform: any
